redroid.py
redroid-1.0.0.dist-info/licenses/LICENSE
redroid-1.0.0.dist-info/METADATA
redroid-1.0.0.dist-info/WHEEL
redroid-1.0.0.dist-info/entry_points.txt
redroid-1.0.0.dist-info/top_level.txt
redroid-1.0.0.dist-info/RECORD
