Metadata-Version: 2.4
Name: redroid
Version: 1.0.0
Summary: Android Security Testing Tool with Emulator Support
Home-page: https://github.com/YoruYagami/Redroid
Author: YoruYagami
License: MIT License
Project-URL: Homepage, https://github.com/YoruYagami/Redroid
Project-URL: Repository, https://github.com/YoruYagami/Redroid
Project-URL: Issues, https://github.com/YoruYagami/Redroid/issues
Keywords: android,security,testing,frida,emulator,adb,mobile,pentesting
Classifier: Development Status :: 4 - Beta
Classifier: Intended Audience :: Developers
Classifier: Intended Audience :: Information Technology
Classifier: Topic :: Security
Classifier: Topic :: Software Development :: Testing
Classifier: License :: OSI Approved :: MIT License
Classifier: Programming Language :: Python :: 3
Classifier: Programming Language :: Python :: 3.7
Classifier: Programming Language :: Python :: 3.8
Classifier: Programming Language :: Python :: 3.9
Classifier: Programming Language :: Python :: 3.10
Classifier: Programming Language :: Python :: 3.11
Classifier: Operating System :: OS Independent
Requires-Python: >=3.7
License-File: LICENSE
Requires-Dist: frida
Requires-Dist: frida-tools
Requires-Dist: psutil
Requires-Dist: requests
Requires-Dist: beautifulsoup4
Requires-Dist: colorama
Requires-Dist: apkleaks
Requires-Dist: objection
Requires-Dist: drozer
Provides-Extra: dev
Requires-Dist: pytest; extra == "dev"
Requires-Dist: black; extra == "dev"
Requires-Dist: flake8; extra == "dev"
Dynamic: home-page
Dynamic: license-file
Dynamic: requires-python
